py_comm/__init__.py
py_comm/singleton.py
py_comm-0.0.1.dist-info/LICENSE
py_comm-0.0.1.dist-info/METADATA
py_comm-0.0.1.dist-info/WHEEL
py_comm-0.0.1.dist-info/top_level.txt
py_comm-0.0.1.dist-info/RECORD
