Metadata-Version: 2.1
Name: py-comm
Version: 0.0.1
Summary: Common utils for python
Home-page: UNKNOWN
Author: UNKNOWN
Author-email: UNKNOWN
License: UNKNOWN
Keywords: pip,commons,common,utils,util
Platform: any
